ismain/__init__.py
ismain/__version__.py
ismain/is_main.py
ismain/py.typed
ismain-0.0.4.dist-info/LICENSE
ismain-0.0.4.dist-info/LICENSE.txt
ismain-0.0.4.dist-info/METADATA
ismain-0.0.4.dist-info/WHEEL
ismain-0.0.4.dist-info/top_level.txt
ismain-0.0.4.dist-info/RECORD
