Metadata-Version: 2.1
Name: ismain
Version: 0.0.4
Summary: prettier test for main
Home-page: https://github.com/jamesabel/ismain
Author: James Abel
Author-email: j@abel.co
License: MIT License
Download-URL: https://github.com/jamesabel/ismain/archive/master.zip
Keywords: utility
Platform: UNKNOWN
